networkd/__init__.py
networkd/networkd.py
networkd-0.1.14.dist-info/LICENSE
networkd-0.1.14.dist-info/METADATA
networkd-0.1.14.dist-info/WHEEL
networkd-0.1.14.dist-info/RECORD
