Metadata-Version: 2.3
Name: networkd
Version: 0.1.14
Summary: A package to quickly embed and analyze abstract data types!
License: MIT
Author: Lorenzo Giamartino
Requires-Python: >=3.9,<4.0
Classifier: License :: OSI Approved :: MIT License
Classifier: Programming Language :: Python :: 3
Classifier: Programming Language :: Python :: 3.9
Classifier: Programming Language :: Python :: 3.10
Classifier: Programming Language :: Python :: 3.11
Classifier: Programming Language :: Python :: 3.12
Classifier: Programming Language :: Python :: 3.13
Requires-Dist: numpy (>=1.22,<3.0)
Requires-Dist: pandas (>=2.0,<3.0)
Project-URL: Homepage, https://github.com/lorenzosg/networkD
Project-URL: Repository, https://github.com/lorenzosg/networkD
